chartpy/__init__.py
chartpy/canvas.py
chartpy/chart.py
chartpy/chartconstants.py
chartpy/engine.py
chartpy/style.py
chartpy/twitter.py
chartpy/dashboard/__init__.py
chartpy/dashboard/layoutcanvas.py
chartpy/dashboard/sessionmanager.py
chartpy/dashboard/sketchcomponents.py
chartpy/report/__init__.py
chartpy/report/common/__init__.py
chartpy/report/common/image.py
chartpy/report/common/report.py
chartpy/report/common/report_block.py
chartpy/report/common/report_component.py
chartpy/report/common/report_section.py
chartpy/report/common/style_table.py
chartpy/report/common/table.py
chartpy/report/components/__init__.py
chartpy/report/components/drawdown/__init__.py
chartpy/report/components/drawdown/drawdown_component.py
chartpy/report/components/drawdown/drawdown_table.py
chartpy/report/components/drawdown/drawdowns_chart.py
chartpy/report/components/drawdown/tests/__init__.py
chartpy/report/components/front_matter/__init__.py
chartpy/report/components/front_matter/contents_page.py
chartpy/report/components/front_matter/title_page.py
chartpy/report/utils/__init__.py
chartpy/report/utils/constants.py
chartpy/report/utils/document_template.py
chartpy/report/utils/style.py
chartpy/report/utils/utils.py
chartpy/report/utils/table_highlighting/__init__.py
chartpy/report/utils/table_highlighting/cell_highlighting.py
chartpy/report/utils/table_highlighting/row_highlighting.py
chartpy/stylesheets/538-chartpy.mplstyle
chartpy/stylesheets/__init__.py
chartpy/stylesheets/chartpy-pyfolio.mplstyle
chartpy/stylesheets/chartpy.mplstyle
chartpy/stylesheets/ggplot-chartpy.mplstyle
chartpy/stylesheets/ggplot-tradtional.mplstyle
chartpy_examples/__init__.py
chartpy_examples/barh.png
chartpy_examples/bokeh.html
chartpy_examples/canvas.png
chartpy_examples/canvas_demo.py
chartpy_examples/chart_demo.py
chartpy_examples/heatmap.png
chartpy_examples/plotly.html
chartpy_examples/plotlyheatmap.png
chartpy_examples/screenshot.png
chartpy_examples/subplot.png
chartpy_examples/surface_example.py
chartpy-0.1.16.dist-info/LICENCE
chartpy-0.1.16.dist-info/METADATA
chartpy-0.1.16.dist-info/WHEEL
chartpy-0.1.16.dist-info/top_level.txt
chartpy-0.1.16.dist-info/RECORD
